doe_xstock/__init__.py
doe_xstock/data.py
doe_xstock/database.py
doe_xstock/end_use_load_profiles.py
doe_xstock/simulate.py
doe_xstock/utilities.py
doe_xstock-2.0.0.dist-info/licenses/LICENSE
doe_xstock-2.0.0.dist-info/METADATA
doe_xstock-2.0.0.dist-info/WHEEL
doe_xstock-2.0.0.dist-info/entry_points.txt
doe_xstock-2.0.0.dist-info/top_level.txt
doe_xstock-2.0.0.dist-info/RECORD
