Metadata-Version: 2.4
Name: doe_xstock
Version: 2.0.0
Summary: Manage DOE's End Use Load Profiles for the U.S. Building Stock.
Home-page: https://github.com/intelligent-environments-lab/doe_xstock
Author: Kingsley Nweye
Author-email: etonwana@yahoo.com
Classifier: Programming Language :: Python :: 3
Classifier: License :: OSI Approved :: MIT License
Classifier: Operating System :: OS Independent
Requires-Python: >=3.7.7
License-File: LICENSE
Requires-Dist: beautifulsoup4
Requires-Dist: eppy
Requires-Dist: pandas
Requires-Dist: platformdirs
Requires-Dist: pyarrow
Requires-Dist: openstudio<=3.10.0
Requires-Dist: requests
Requires-Dist: simplejson
Requires-Dist: pyyaml
Dynamic: author
Dynamic: author-email
Dynamic: classifier
Dynamic: description
Dynamic: description-content-type
Dynamic: home-page
Dynamic: license-file
Dynamic: requires-dist
Dynamic: requires-python
Dynamic: summary
